paasword/__init__.py
paasword/middleware.py
paasword-1.0.1.dist-info/LICENSE
paasword-1.0.1.dist-info/METADATA
paasword-1.0.1.dist-info/WHEEL
paasword-1.0.1.dist-info/top_level.txt
paasword-1.0.1.dist-info/RECORD
